spb_curate/__init__.py
spb_curate/abstract/__init__.py
spb_curate/abstract/api/__init__.py
spb_curate/abstract/api/resource.py
spb_curate/abstract/superb_ai_object.py
spb_curate/api_requestor.py
spb_curate/config.py
spb_curate/curate/__init__.py
spb_curate/curate/api/__init__.py
spb_curate/curate/api/abstract.py
spb_curate/curate/api/curate.py
spb_curate/curate/api/enums.py
spb_curate/curate/api/job.py
spb_curate/curate/api/model_diagnosis.py
spb_curate/curate/api/settings.py
spb_curate/curate/model/__init__.py
spb_curate/curate/model/annotation_types.py
spb_curate/error.py
spb_curate/http_client.py
spb_curate/object_mapping.py
spb_curate/superb_ai_response.py
spb_curate/util.py
spb_curate/version.py
superb_ai_curate-1.5.0.dist-info/LICENSE
superb_ai_curate-1.5.0.dist-info/METADATA
superb_ai_curate-1.5.0.dist-info/WHEEL
superb_ai_curate-1.5.0.dist-info/RECORD
