Metadata-Version: 2.1
Name: superb-ai-curate
Version: 1.5.0
Summary: The official Superb AI Curate client for Python
Home-page: https://superb-ai.com/
License: MIT
Keywords: superb ai,superbapi,tasks,categorization,annotation,labeling,dataops,mlops,curation
Author: Superb AI
Author-email: support@superb-ai.com
Requires-Python: >=3.7,<4.0
Classifier: Development Status :: 5 - Production/Stable
Classifier: Intended Audience :: Developers
Classifier: Intended Audience :: Science/Research
Classifier: License :: OSI Approved :: MIT License
Classifier: Natural Language :: English
Classifier: Programming Language :: Python
Classifier: Programming Language :: Python :: 3
Classifier: Programming Language :: Python :: 3.7
Classifier: Programming Language :: Python :: 3.8
Classifier: Programming Language :: Python :: 3.9
Classifier: Programming Language :: Python :: 3.10
Classifier: Programming Language :: Python :: 3.11
Classifier: Programming Language :: Python :: 3.12
Classifier: Topic :: Scientific/Engineering :: Artificial Intelligence
Classifier: Topic :: Software Development :: Libraries
Provides-Extra: dev
Provides-Extra: docs
Requires-Dist: Sphinx ; extra == "docs"
Requires-Dist: aiohttp (>=3.8.0,<3.9.0) ; python_version >= "3.7" and python_version < "3.12"
Requires-Dist: aiohttp (>=3.9.0) ; python_version >= "3.12"
Requires-Dist: black ; extra == "dev"
Requires-Dist: coveralls ; extra == "dev"
Requires-Dist: isort ; extra == "dev"
Requires-Dist: pytest ; extra == "dev"
Requires-Dist: pytest-asyncio ; extra == "dev"
Requires-Dist: pytest-cov ; extra == "dev"
Requires-Dist: requests (>=2.20.0,<3.0.0)
Requires-Dist: sphinx-autodoc-typehints (>=1.19.4,<2.0.0) ; extra == "docs"
Requires-Dist: sphinx-pyproject ; extra == "docs"
Requires-Dist: sphinx-rtd-theme ; extra == "docs"
Requires-Dist: sphinxcontrib-napoleon ; extra == "docs"
Project-URL: Documentation, https://docs.superb-ai.com/reference/superb-curate-sdk-overview
Project-URL: Repository, https://github.com/Superb-AI-Suite/superb-ai-curate-python
